ecsctrl/VERSION
ecsctrl/__init__.py
ecsctrl/__main__.py
ecsctrl/boto_client.py
ecsctrl/cli.py
ecsctrl/loader.py
ecsctrl/service_updater.py
ecsctrl/yaml_converter.py
ecsctrl/dump/__init__.py
ecsctrl/dump/secrets.py
ecsctrl-0.5.2.dist-info/METADATA
ecsctrl-0.5.2.dist-info/WHEEL
ecsctrl-0.5.2.dist-info/entry_points.txt
ecsctrl-0.5.2.dist-info/top_level.txt
ecsctrl-0.5.2.dist-info/RECORD
