Metadata-Version: 2.4
Name: ECSctrl
Version: 0.5.2
Summary: ECSctrl - utility to deploy ECS services for humans
Home-page: http://github.com/wlatanowicz/ecsctrl
Author: Wiktor Latanowicz
Author-email: ecsctrl@wiktor.latanowicz.com
License: MIT
Classifier: Programming Language :: Python :: 3
Classifier: License :: OSI Approved :: MIT License
Classifier: Operating System :: OS Independent
Requires-Python: >=3.6
Requires-Dist: PyYAML>=6.0
Requires-Dist: boto3>=1.23.5
Requires-Dist: Jinja2>=3.1.2
Requires-Dist: click>=8.1.3
Dynamic: author
Dynamic: author-email
Dynamic: classifier
Dynamic: description
Dynamic: description-content-type
Dynamic: home-page
Dynamic: license
Dynamic: requires-dist
Dynamic: requires-python
Dynamic: summary
